efsync2/__init__.py
efsync2/efsync_cli.py
efsync2/logger.py
efsync2/main.py
efsync2/test/__init__.py
efsync2/test/test_main.py
efsync2/test/test_utils.py
efsync2/utils/__init__.py
efsync2/utils/config/__init__.py
efsync2/utils/config/get_boto3_client.py
efsync2/utils/config/load_args_from_yaml.py
efsync2/utils/config/load_config.py
efsync2/utils/config/read_requirements_from_file.py
efsync2/utils/config/validate_config.py
efsync2/utils/ec2/__init__.py
efsync2/utils/ec2/create_user_data.py
efsync2/utils/ec2/custom_waiter.py
efsync2/utils/ec2/ec2_main.py
efsync2/utils/ec2/ec2_waiter.py
efsync2/utils/efs/__init__.py
efsync2/utils/efs/describe_efs.py
efsync2/utils/iam_profile/__init__.py
efsync2/utils/iam_profile/iam_profile.py
efsync2/utils/security_group/__init__.py
efsync2/utils/security_group/ec2_security_group.py
efsync2/utils/ssh/__init__.py
efsync2/utils/ssh/createSSHClient.py
efsync2/utils/ssh/scp_to_ec2.py
efsync2/utils/ssh/ssh_key.py
efsync2-1.0.dist-info/LICENSE
efsync2-1.0.dist-info/METADATA
efsync2-1.0.dist-info/WHEEL
efsync2-1.0.dist-info/entry_points.txt
efsync2-1.0.dist-info/top_level.txt
efsync2-1.0.dist-info/RECORD
