Metadata-Version: 2.1
Name: efsync2
Version: 1.0
Summary: A CLI/SDK which automatically uploads pip packages and directories to aws efs to be used in aws lambda
Home-page: https://github.com/sean-bailey
Author: Sean Bailey
Author-email: seanbailey518@gmail.com
License: UNKNOWN
Platform: UNKNOWN
Classifier: Programming Language :: Python :: 3
Classifier: License :: OSI Approved :: MIT License
Classifier: Operating System :: OS Independent
Requires-Python: >=3.6
License-File: LICENSE
Requires-Dist: scp
Requires-Dist: paramiko
Requires-Dist: boto3
Requires-Dist: pyaml
